<?xml version="1.0" encoding="utf-8"?>
<!--*** Do not edit this file. ***-->
<!--*** Importing invalid data can cause unexpected behaviour and potential data loss. ***-->
<!--Created: 2/7/2021 9:58:35 AM-->
<ComponentCatalogUserModelSettings Version="1.0">
  <RecentItems>
    <IDString>CatalogSystemComponentDetailItem?000001024</IDString>
    <IDString>CatalogSystemComponentMacroItem?001000077</IDString>
    <IDString>CatalogSystemComponentMacroItem?031000018</IDString>
    <IDString>CatalogSystemComponentMacroItem?001000068</IDString>
    <IDString>CatalogSystemComponentJointItem?000000144</IDString>
    <IDString>CatalogSystemComponentJointItem?000000141</IDString>
    <IDString>CatalogSystemComponentDetailItem?000001047</IDString>
  </RecentItems>
  <ExpandedGroupPlaceholders>
    <Path>albl_Root_fixed_group_name//Engenharia Básica</Path>
    <Path>albl_Root_fixed_group_name//Engenharia Básica//Conexões de viga com viga</Path>
    <Path>albl_Root_fixed_group_name//Engenharia Básica//Detalhes</Path>
    <Path>albl_Root_fixed_group_name//Engenharia Básica//Conexões de joists</Path>
    <Path>albl_Root_fixed_group_name//Engenharia Básica//Armadura de concreto moldado in-loco</Path>
    <Path>albl_Root_fixed_group_name//Engenharia Básica//Componentes pré-engenheirados</Path>
  </ExpandedGroupPlaceholders>
</ComponentCatalogUserModelSettings>